colorlab.py
setup.py
colorlab.egg-info/PKG-INFO
colorlab.egg-info/SOURCES.txt
colorlab.egg-info/dependency_links.txt
colorlab.egg-info/top_level.txt