Metadata-Version: 1.0
Name: colorlab
Version: 0.1
Summary: Color manipulation library for python
Home-page: http://github.com/awagner83/ColorLab
Author: Adam Wagner
Author-email: awagner83@gmail.com
License: UNKNOWN
Platform: UNKNOWN
